marqus_manner/__init__.py
marqus_manner/py.typed
marqus_manner/version.py
marqus_manner-1.0.0.dist-info/licenses/LICENSE
marqus_manner-1.0.0.dist-info/METADATA
marqus_manner-1.0.0.dist-info/WHEEL
marqus_manner-1.0.0.dist-info/entry_points.txt
marqus_manner-1.0.0.dist-info/top_level.txt
marqus_manner-1.0.0.dist-info/RECORD
