Metadata-Version: 2.4
Name: marqus-manner
Version: 1.0.0
Summary: Security scanner for Model Context Protocol (MCP) servers
Home-page: https://github.com/marqus-ai/marqus-manner
Author: Marqus AI
Author-email: Marqus AI <dev-support@marqus.ai>
License-Expression: MIT
Project-URL: Homepage, https://github.com/marqus-ai/marqus-manner
Project-URL: Bug Tracker, https://github.com/marqus-ai/marqus-manner/issues
Project-URL: Documentation, https://github.com/marqus-ai/marqus-manner/blob/main/README.md
Keywords: security,mcp,aibom,scanning,vulnerability,ai-security
Classifier: Development Status :: 5 - Production/Stable
Classifier: Intended Audience :: Developers
Classifier: Intended Audience :: Information Technology
Classifier: Intended Audience :: System Administrators
Classifier: Operating System :: OS Independent
Classifier: Programming Language :: Python :: 3
Classifier: Programming Language :: Python :: 3.8
Classifier: Programming Language :: Python :: 3.9
Classifier: Programming Language :: Python :: 3.10
Classifier: Programming Language :: Python :: 3.11
Classifier: Topic :: Security
Classifier: Topic :: Software Development :: Libraries :: Python Modules
Requires-Python: >=3.8
License-File: LICENSE
Requires-Dist: rich>=10.0.0
Requires-Dist: pyjson5>=1.6.0
Requires-Dist: lark>=1.1.0
Requires-Dist: pydantic>=2.0.0
Requires-Dist: aiohttp>=3.8.0
Requires-Dist: asyncio>=3.4.3
Provides-Extra: dev
Requires-Dist: pytest>=7.0.0; extra == "dev"
Requires-Dist: pytest-cov>=4.0.0; extra == "dev"
Requires-Dist: pytest-asyncio>=0.21.0; extra == "dev"
Requires-Dist: black>=23.0.0; extra == "dev"
Requires-Dist: isort>=5.0.0; extra == "dev"
Requires-Dist: flake8>=6.0.0; extra == "dev"
Requires-Dist: mypy>=1.0.0; extra == "dev"
Requires-Dist: build>=0.8.0; extra == "dev"
Requires-Dist: twine>=4.0.0; extra == "dev"
Provides-Extra: test
Requires-Dist: pytest>=7.0.0; extra == "test"
Requires-Dist: pytest-cov>=4.0.0; extra == "test"
Dynamic: author
Dynamic: home-page
Dynamic: license-file
Dynamic: requires-python
